dungAnalyzer/Analyzer.py
dungAnalyzer/__init__.py
dungAnalyzer/BanglaStemmer/BanglaStemmer.py
dungAnalyzer/BanglaStemmer/__init__.py
dungAnalyzer/Normalizer/Normalizer.py
dungAnalyzer/Normalizer/__init__.py
dungAnalyzer/Stemmer/Stemmer.py
dungAnalyzer/Stemmer/__init__.py
dungAnalyzer/StopWordProcessor/StopWordProcessor.py
dungAnalyzer/StopWordProcessor/__init__.py
dungAnalyzer/resources/stopwords-bn.txt
dungAnalyzer-0.3.4.dist-info/DESCRIPTION.rst
dungAnalyzer-0.3.4.dist-info/METADATA
dungAnalyzer-0.3.4.dist-info/RECORD
dungAnalyzer-0.3.4.dist-info/WHEEL
dungAnalyzer-0.3.4.dist-info/metadata.json
dungAnalyzer-0.3.4.dist-info/top_level.txt
