Metadata-Version: 2.0
Name: dungAnalyzer
Version: 0.3.4
Summary: Stemming words and removal of stop words
Home-page: UNKNOWN
Author: algomatrix
Author-email: maruf@algomatrix.co
License: MIT
Platform: UNKNOWN
Classifier: Development Status :: 2 - Pre-Alpha
Classifier: Intended Audience :: Developers
Classifier: Intended Audience :: Education
Classifier: License :: OSI Approved :: MIT License
Classifier: Natural Language :: Bengali
Classifier: Operating System :: OS Independent
Classifier: Programming Language :: Python
Classifier: Programming Language :: Python :: 3
Classifier: Programming Language :: Python :: 3.6
Classifier: Topic :: Text Processing
Requires-Dist: nltk (==3.2.5)
